sifca_utils/__init__.py
sifca_utils/histo_utils.py
sifca_utils/plotting.py
sifca_utils-0.1.dist-info/DESCRIPTION.rst
sifca_utils-0.1.dist-info/METADATA
sifca_utils-0.1.dist-info/RECORD
sifca_utils-0.1.dist-info/WHEEL
sifca_utils-0.1.dist-info/metadata.json
sifca_utils-0.1.dist-info/top_level.txt
