Metadata-Version: 2.0
Name: sifca-utils
Version: 0.1
Summary: SIFCA analysis utils
Home-page: https://gitlab.cern.ch/sifca/sifca-utils
Author: Jordi Duarte-Campderros
Author-email: Jordi.Duarte.Campderros@cern.ch
License: UNKNOWN
Platform: UNKNOWN
Classifier: Programming Language :: Python :: 2.7
Classifier: License :: OSI Approved :: GNU General Public License v3 or later (GPLv3+)
Classifier: Operating System :: OS Independent
Classifier: Development Status :: 4 - Beta
